pioled_display_plugin/__init__.py
pioled_display_plugin/post_install.sh
pioled_display_plugin/pre_uninstall.sh
pioled_display_plugin-0.5.0.dist-info/licenses/LICENSE.txt
pioled_display_plugin-0.5.0.dist-info/METADATA
pioled_display_plugin-0.5.0.dist-info/WHEEL
pioled_display_plugin-0.5.0.dist-info/entry_points.txt
pioled_display_plugin-0.5.0.dist-info/top_level.txt
pioled_display_plugin-0.5.0.dist-info/RECORD
