Metadata-Version: 2.4
Name: pioled-display-plugin
Version: 0.5.0
Summary: Use an OLED display with your Pioreactor
Home-page: https://github.com/Pioreactor/PiOLED-display-plugin
Author: Pioreactor
Author-email: hello@pioreactor.com
License-File: LICENSE.txt
Requires-Dist: adafruit-circuitpython-ssd1306==2.12.16
Requires-Dist: Pillow==10.1.0
Dynamic: author
Dynamic: author-email
Dynamic: description
Dynamic: description-content-type
Dynamic: home-page
Dynamic: license-file
Dynamic: requires-dist
Dynamic: summary
